adafruit_fxas21002c.py
adafruit_circuitpython_fxas21002c-3.0.8.dist-info/licenses/LICENSE
adafruit_circuitpython_fxas21002c-3.0.8.dist-info/METADATA
adafruit_circuitpython_fxas21002c-3.0.8.dist-info/WHEEL
adafruit_circuitpython_fxas21002c-3.0.8.dist-info/top_level.txt
adafruit_circuitpython_fxas21002c-3.0.8.dist-info/RECORD
