Metadata-Version: 2.4
Name: adafruit-circuitpython-fxas21002c
Version: 3.0.8
Summary: CircuitPython library for NXP FXAS21002C gyroscope.
Author-email: Adafruit Industries <circuitpython@adafruit.com>
License: MIT
Project-URL: Homepage, https://github.com/adafruit/Adafruit_CircuitPython_FXAS21002C
Keywords: adafruit,fxas21002c,gyro,gyroscope,nxp,breakout,hardware,micropython,circuitpython
Classifier: Intended Audience :: Developers
Classifier: Topic :: Software Development :: Libraries
Classifier: Topic :: Software Development :: Embedded Systems
Classifier: Topic :: System :: Hardware
Classifier: License :: OSI Approved :: MIT License
Classifier: Programming Language :: Python :: 3
License-File: LICENSE
Requires-Dist: Adafruit-Blinka
Requires-Dist: adafruit-circuitpython-busdevice>=2.2.5
Provides-Extra: optional
Dynamic: license-file
